animax/__init__.py
animax/__main__.py
animax-0.1.0.dist-info/METADATA
animax-0.1.0.dist-info/WHEEL
animax-0.1.0.dist-info/entry_points.txt
animax-0.1.0.dist-info/licenses/LICENSE
animax-0.1.0.dist-info/RECORD
