Metadata-Version: 2.4
Name: animax
Version: 0.1.0
Summary: Your personal anima foundry
Project-URL: Homepage, https://github.com/sumukshashidhar/anima
Project-URL: Repository, https://github.com/sumukshashidhar/anima
Author-email: Sumuk Shashidhar <sumuks2@illinois.edu>
License:                                  Apache License
License-File: LICENSE
Requires-Python: >=3.11
Requires-Dist: loguru>=0.7.3
